{
    "configurations": [
        {
            "name": "Linux",
            "includePath": [
                "${workspaceFolder}/**",
                "/usr/lib/habanatools/include/**",
                "${workspaceFolder}/doc/**"
            ],
            "defines": [],
            "compilerPath": "/usr/bin/g++",
            "cStandard": "c23",
            "cppStandard": "c++17",
            "intelliSenseMode": "linux-gcc-x86",
            "configurationProvider": "ms-vscode.cpptools"
        }
    ],
    "version": 4
}